mini_face/__init__.py
mini_face/abseil_dll.dll
mini_face/action_unit.py
mini_face/api.cp312-win_amd64.pyd
mini_face/api.lib
mini_face/gaze.py
mini_face/libgcc_s_seh-1.dll
mini_face/libgfortran-5.dll
mini_face/liblapack.dll
mini_face/libprotobuf.dll
mini_face/libquadmath-0.dll
mini_face/libwinpthread-1.dll
mini_face/mode.py
mini_face/openblas.dll
mini_face/opencv_calib3d4.dll
mini_face/opencv_core4.dll
mini_face/opencv_dnn4.dll
mini_face/opencv_features2d4.dll
mini_face/opencv_flann4.dll
mini_face/opencv_imgproc4.dll
mini_face/opencv_objdetect4.dll
mini_face/zlib1.dll
mini_face-0.1.3.data/data/vcpkg.json
mini_face-0.1.3.dist-info/LICENSE
mini_face-0.1.3.dist-info/METADATA
mini_face-0.1.3.dist-info/WHEEL
mini_face-0.1.3.dist-info/top_level.txt
mini_face-0.1.3.dist-info/RECORD
