Metadata-Version: 2.1
Name: mini-face
Version: 0.1.3
Summary: A minimalist Python wrapper for OpenFace library
Author-email: Igor Swat <iswat@student.agh.edu.pl>, Jan Smółka <jp.smolka@gmail.com>
License: BSD 3-Clause License
Project-URL: repository, https://github.com/child-lab-uj/mini-face
Keywords: OpenFace,vcpkg,pybind11,scikit-build,cpp
Requires-Python: >=3.12
License-File: LICENSE
Requires-Dist: numpy>=1.21
